pset_utils/__init__.py
pset_utils-0.5.dist-info/DESCRIPTION.rst
pset_utils-0.5.dist-info/METADATA
pset_utils-0.5.dist-info/RECORD
pset_utils-0.5.dist-info/WHEEL
pset_utils-0.5.dist-info/metadata.json
pset_utils-0.5.dist-info/top_level.txt
