Metadata-Version: 2.0
Name: pset-utils
Version: 0.5
Summary: Utilities to help with pyplot
Home-page: http://github.com/zyxw59/pset_utils
Author: Emily Crandall Fleischman
Author-email: emilycf@mit.edu
License: MIT
Platform: UNKNOWN
Requires-Dist: cycler
